<?xml version="1.0" encoding="UTF-8"?>
<databaseChangeLog
        xmlns="http://www.liquibase.org/xml/ns/dbchangelog"
        xmlns:xsi="http://www.w3.org/2001/XMLSchema-instance"
        xsi:schemaLocation="http://www.liquibase.org/xml/ns/dbchangelog
         http://www.liquibase.org/xml/ns/dbchangelog/dbchangelog-3.2.xsd">

    <!--
    <changeSet id="1_create_customer_table" author="larsostling">
        <createTable tableName="customer">
            <column name="id" type="int">
                <constraints primaryKey="true" nullable="false"/>
            </column>
            <column name="firstname" type="varchar(100)">
                <constraints nullable="false"/>
            </column>
            <column name="lastname" type="varchar(100)">
                <constraints nullable="false"/>
            </column>
        </createTable>
    </changeSet>
    -->

    <!--
    <changeSet id="2_add_reference_customers" author="larsostling">
        <insert tableName="customer">
            <column name="id" value="1"/>
            <column name="firstname" value="Regular"/>
            <column name="lastname" value="Customer"/>
        </insert>
        <insert tableName="customer">
            <column name="id" value="2"/>
            <column name="firstname" value="Premium"/>
            <column name="lastname" value="Customer"/>
        </insert>
    </changeSet>
    -->

</databaseChangeLog>
